Metadata-Version: 2.4
Name: libintx-cu128-openmpi
Version: 0.0.1
Summary: Python bindings to LibintX code
Home-page: https://github.com/terra-quantum-io/tq-libintx
Author: Roman Ellerbrock
Author-email: re@terraquantum.swiss
Classifier: Programming Language :: Python :: 3
Classifier: Operating System :: OS Independent
Requires-Python: >=3.11
Requires-Dist: setuptools
Requires-Dist: wheel
Dynamic: author
Dynamic: author-email
Dynamic: classifier
Dynamic: home-page
Dynamic: requires-dist
Dynamic: requires-python
Dynamic: summary
